frontline-0.1.2.dist-info/METADATA
frontline-0.1.2.dist-info/WHEEL
frontline-0.1.2.dist-info/licenses/LICENSE.md
frontline/__init__.py
frontline/version.py
frontline-0.1.2.dist-info/RECORD
